cs233/Labs/Lab3/mux.v
// output = A (when control == 0) or B (when control == 1)
module mux2(out, A, B, control);
    output out;
    input  A, B;
    input  control;
    wire   wA, wB, not_control;

    not n1(not_control, control);
    and a1(wA, A, not_control);
    and a2(wB, B, control);
    or  o1(out, wA, wB);
endmodule // mux2

// output = A (when control == 00) or B (when control == 01) or
//          C (when control == 10) or D (when control == 11)
module mux4(out, A, B, C, D, control);
    output      out;
    input       A, B, C, D;
    input [1:0] control;
    wire w1, w2;

    mux2 m1(w1, A, B, control[0]);
    mux2 m2(w2, C, D, control[0]);
    mux2 m3(out, w1, w2, control[1]);

endmodule // mux4

cs233/Labs/Lab3/logicunit.v
// 00 - AND, 01 - OR, 10 - NOR, 11 - XOR
module logicunit(out, A, B, control);
    output      out;
    input       A, B;
    input [1:0] control;
    wire w1, w2, w3, w4;
    and a1(w1, A, B);
    or o2(w2, A, B);
    nor n3(w3, A, B);
    xor x4(w4, A, B);
    mux4 m1(out, w1, w2, w3, w4, control);
endmodule // logicunit

cs233/Labs/Lab3/alu1.v
module full_adder(sum, cout, a, b, cin);
    output sum, cout;
    input  a, b, cin;
    wire   partial_s, partial_c1, partial_c2;

    xor x0(partial_s, a, b);
    xor x1(sum, partial_s, cin);
    and a0(partial_c1, a, b);
    and a1(partial_c2, partial_s, cin);
    or  o1(cout, partial_c1, partial_c2);
endmodule // full_adder

`define ALU_ADD    3'h2 //010
`define ALU_SUB    3'h3 //011
`define ALU_AND    3'h4 //100
`define ALU_OR     3'h5 //101
`define ALU_NOR    3'h6 //110
`define ALU_XOR    3'h7 //111

// 01x - arithmetic, 1xx - logic
module alu1(out, carryout, A, B, carryin, control);
    output      out, carryout;
    input       A, B, carryin;
    input [2:0] control;
    wire addOut, logicOut, wB;

    xor x3(wB, B, control[0]);
    full_adder f1(addOut, carryout, A, wB, carryin);
    logicunit l1(logicOut, A, B, control[1:0]);
    mux2 m2(out, addOut, logicOut, control[2]);

endmodule // alu1

cs233/Labs/Lab3/alu1_tb.v
module alu1_test;

reg A = 0;
always #1 A = !A;
reg B = 0;
always #2 B = !B;
reg Cin = 0;
always #4 Cin = !Cin;


reg [2:0] control = 0;

initial begin
    $dumpfile("alu1.vcd");
    $dumpvars(0, alu1_test);

    // control is initially 0
    # 16 control = 1; // wait 16 time units (why 16?) and then set it to 1
    # 16 control = 2; // wait 16 time units and then set it to 2
    # 16 control = 3; // wait 16 time units and then set it to 3
    # 16 control = 4; // wait 16 time units and then set it to 4
    # 16 control = 5; // wait 16 time units and then set it to 5
    # 16 control = 6; // wait 16 time units and then set it to 6
    # 16 control = 7; // wait 16 time units and then set it to 7
    # 16 $finish; // wait 16 time units and then end the simulation
end

wire out, Cout;
alu1 a1(out, Cout, A, B, Cin, control);

// you really should be using gtkwave instead

initial begin
    $display("A B i o s out");
    $monitor("%d %d %d %d %d %d (at time %t)", A, B, Cin, Cout, control, out, $time);
end

endmodule

cs233/Labs/Lab3/alu1.vcd
$date
	Tue Sep 19 22:06:23 2017
$end
$version
	Icarus Verilog
$end
$timescale
	1s
$end
$scope module alu1_test $end
$var wire 1 ! Cout $end
$var wire 1 " out $end
$var reg 1 # A $end
$var reg 1 $ B $end
$var reg 1 % Cin $end
$var reg 3 & control [2:0] $end
$scope module a1 $end
$var wire 1 ' A $end
$var wire 1 ( B $end
$var wire 1 ) addOut $end
$var wire 1 * carryin $end
$var wire 1 ! carryout $end
$var wire 3 + control [2:0] $end
$var wire 1 , logicOut $end
$var wire 1 " out $end
$var wire 1 - wB $end
$scope module f1 $end
$var wire 1 ' a $end
$var wire 1 - b $end
$var wire 1 * cin $end
$var wire 1 ! cout $end
$var wire 1 . partial_c1 $end
$var wire 1 / partial_c2 $end
$var wire 1 0 partial_s $end
$var wire 1 ) sum $end
$upscope $end
$scope module l1 $end
$var wire 1 ' A $end
$var wire 1 ( B $end
$var wire 2 1 control [1:0] $end
$var wire 1 , out $end
$var wire 1 2 w1 $end
$var wire 1 3 w2 $end
$var wire 1 4 w3 $end
$var wire 1 5 w4 $end
$scope module m1 $end
$var wire 1 2 A $end
$var wire 1 3 B $end
$var wire 1 4 C $end
$var wire 1 5 D $end
$var wire 2 6 control [1:0] $end
$var wire 1 , out $end
$var wire 1 7 w1 $end
$var wire 1 8 w2 $end
$scope module m1 $end
$var wire 1 2 A $end
$var wire 1 3 B $end
$var wire 1 9 control $end
$var wire 1 : not_control $end
$var wire 1 7 out $end
$var wire 1 ; wA $end
$var wire 1 < wB $end
$upscope $end
$scope module m2 $end
$var wire 1 4 A $end
$var wire 1 5 B $end
$var wire 1 = control $end
$var wire 1 > not_control $end
$var wire 1 8 out $end
$var wire 1 ? wA $end
$var wire 1 @ wB $end
$upscope $end
$scope module m3 $end
$var wire 1 7 A $end
$var wire 1 8 B $end
$var wire 1 A control $end
$var wire 1 B not_control $end
$var wire 1 , out $end
$var wire 1 C wA $end
$var wire 1 D wB $end
$upscope $end
$upscope $end
$upscope $end
$scope module m2 $end
$var wire 1 ) A $end
$var wire 1 , B $end
$var wire 1 E control $end
$var wire 1 F not_control $end
$var wire 1 " out $end
$var wire 1 G wA $end
$var wire 1 H wB $end
$upscope $end
$upscope $end
$upscope $end
$enddefinitions $end
#0
$dumpvars
0H
0G
1F
0E
0D
0C
1B
0A
0@
1?
1>
0=
0<
0;
1:
09
18
07
b0 6
05
14
03
02
b0 1
00
0/
0.
0-
0,
b0 +
0*
0)
0(
0'
b0 &
0%
0$
0#
0"
0!
$end
#1
1"
1G
08
1)
0?
10
13
04
15
1#
1'
#2
1-
0#
0'
1$
1(
#3
1,
0"
1C
0G
17
0)
1!
1;
00
1.
12
05
1#
1'
#4
0,
0C
07
18
1"
0!
0;
1?
1G
0.
0-
02
03
14
1)
0#
0'
0$
0(
1%
1*
#5
0"
0G
1!
08
0)
1/
0?
10
13
04
15
1#
1'
#6
1-
0#
0'
1$
1(
#7
1,
1"
1C
1G
17
1)
0/
1;
00
1.
12
05
1#
1'
#8
0,
0C
07
18
0"
0!
0;
1?
0G
0.
0-
02
03
14
0)
0#
0'
0$
0(
0%
0*
#9
1"
1G
08
1)
0?
10
13
04
15
1#
1'
#10
1-
0#
0'
1$
1(
#11
1,
0"
1C
0G
17
0)
1!
1;
00
1.
12
05
1#
1'
#12
0,
0C
07
18
1"
0!
0;
1?
1G
0.
0-
02
03
14
1)
0#
0'
0$
0(
1%
1*
#13
0"
0G
1!
08
0)
1/
0?
10
13
04
15
1#
1'
#14
1-
0#
0'
1$
1(
#15
1,
1"
1C
1G
17
1)
0/
1;
00
1.
12
05
1#
1'
#16
0,
0C
07
08
1"
0:
0>
0!
0;
0?
1G
19
1=
10
0.
02
03
14
1)
b1 1
b1 6
0#
0'
0$
0(
0%
0*
b1 &
b1 +
#17
1,
0"
1C
0G
17
18
0)
1!
1<
1@
00
1.
13
04
15
1#
1'
#18
0!
0.
0-
0#
0'
1$
1(
#19
1"
1G
08
1)
0@
10
12
05
1#
1'
#20
0,
0C
07
0"
0<
0G
1!
1-
02
03
14
0)
1/
0#
0'
0$
0(
1%
1*
#21
1,
1"
1C
1G
17
18
1)
0/
1<
1@
00
1.
13
04
15
1#
1'
#22
0!
0.
0-
0#
0'
1$
1(
#23
0"
0G
1!
08
0)
1/
0@
10
12
05
1#
1'
#24
0,
0C
07
1"
0<
1G
0!
1-
02
03
14
1)
0/
0#
0'
0$
0(
0%
0*
#25
1,
0"
1C
0G
17
18
0)
1!
1<
1@
00
1.
13
04
15
1#
1'
#26
0!
0.
0-
0#
0'
1$
1(
#27
1"
1G
08
1)
0@
10
12
05
1#
1'
#28
0,
0C
07
0"
0<
0G
1!
1-
02
03
14
0)
1/
0#
0'
0$
0(
1%
1*
#29
1,
1"
1C
1G
17
18
1)
0/
1<
1@
00
1.
13
04
15
1#
1'
#30
0!
0.
0-
0#
0'
1$
1(
#31
0"
0G
1!
08
0)
1/
0@
10
12
05
1#
1'
#32
1D
18
1,
1?
0C
07
0"
1:
1>
0B
0<
0G
0!
09
0=
1A
00
02
03
14
0)
0/
b10 1
b10 6
0#
0'
0$
0(
0%
0*
b10 &
b10 +
#33
0,
1"
0D
1G
08
1)
0?
10
13
04
15
1#
1'
#34
1-
0#
0'
1$
1(
#35
0"
0G
17
0)
1!
1;
00
1.
12
05
1#
1'
#36
1,
1D
07
18
1"
0!
0;
1?
1G
0.
0-
02
03
14
1)
0#
0'
0$
0(
1%
1*
#37
0,
0"
0D
0G
1!
08
0)
1/
0?
10
13
04
15
1#
1'
#38
1-
0#
0'
1$
1(
#39
1"
1G
17
1)
0/
1;
00
1.
12
05
1#
1'
#40
1,
1D
07
18
0"
0!
0;
1?
0G
0.
0-
02
03
14
0)
0#
0'
0$
0(
0%
0*
#41
0,
1"
0D
1G
08
1)
0?
10
13
04
15
1#
1'
#42
1-
0#
0'
1$
1(
#43
0"
0G
17
0)
1!
1;
00
1.
12
05
1#
1'
#44
1,
1D
07
18
1"
0!
0;
1?
1G
0.
0-
02
03
14
1)
0#
0'
0$
0(
1%
1*
#45
0,
0"
0D
0G
1!
08
0)
1/
0?
10
13
04
15
1#
1'
#46
1-
0#
0'
1$
1(
#47
1"
1G
17
1)
0/
1;
00
1.
12
05
1#
1'
#48
0,
0D
07
08
1"
0:
0>
0!
0;
0?
1G
19
1=
10
0.
02
03
14
1)
b11 1
b11 6
0#
0'
0$
0(
0%
0*
b11 &
b11 +
#49
1,
0"
1D
0G
17
18
0)
1!
1<
1@
00
1.
13
04
15
1#
1'
#50
0!
0.
0-
0#
0'
1$
1(
#51
0,
1"
0D
1G
08
1)
0@
10
12
05
1#
1'
#52
07
0"
0<
0G
1!
1-
02
03
14
0)
1/
0#
0'
0$
0(
1%
1*
#53
1,
1"
1D
1G
17
18
1)
0/
1<
1@
00
1.
13
04
15
1#
1'
#54
0!
0.
0-
0#
0'
1$
1(
#55
0,
0"
0D
0G
1!
08
0)
1/
0@
10
12
05
1#
1'
#56
07
1"
0<
1G
0!
1-
02
03
14
1)
0/
0#
0'
0$
0(
0%
0*
#57
1,
0"
1D
0G
17
18
0)
1!
1<
1@
00
1.
13
04
15
1#
1'
#58
0!
0.
0-
0#
0'
1$
1(
#59
0,
1"
0D
1G
08
1)
0@
10
12
05
1#
1'
#60
07
0"
0<
0G
1!
1-
02
03
14
0)
1/
0#
0'
0$
0(
1%
1*
#61
1,
1"
1D
1G
17
18
1)
0/
1<
1@
00
1.
13
04
15
1#
1'
#62
0!
0.
0-
0#
0'
1$
1(
#63
0,
0"
0D
0G
1!
08
0)
1/
0@
10
12
05
1#
1'
#64
18
1?
07
1:
1>
1B
0<
0!
09
0=
0A
0F
00
02
03
14
0)
0/
b0 1
b0 6
1E
0#
0'
0$
0(
0%
0*
b100 &
b100 +
#65
08
1)
0?
10
13
04
15
1#
1'
#66
1-
0#
0'
1$
1(
#67
1"
1H
1,
1C
17
0)
1!
1;
00
1.
12
05
1#
1'
#68
0"
0H
0,
0C
07
18
0!
0;
1?
0.
0-
02
03
14
1)
0#
0'
0$
0(
1%
1*
#69
1!
08
0)
1/
0?
10
13
04
15
1#
1'
#70
1-
0#
0'
1$
1(
#71
1"
1H
1,
1C
17
1)
0/
1;
00
1.
12
05
1#
1'
#72
0"
0H
0,
0C
07
18
0!
0;
1?
0.
0-
02
03
14
0)
0#
0'
0$
0(
0%
0*
#73
08
1)
0?
10
13
04
15
1#
1'
#74
1-
0#
0'
1$
1(
#75
1"
1H
1,
1C
17
0)
1!
1;
00
1.
12
05
1#
1'
#76
0"
0H
0,
0C
07
18
0!
0;
1?
0.
0-
02
03
14
1)
0#
0'
0$
0(
1%
1*
#77
1!
08
0)
1/
0?
10
13
04
15
1#
1'
#78
1-
0#
0'
1$
1(
#79
1"
1H
1,
1C
17
1)
0/
1;
00
1.
12
05
1#
1'
#80
0"
0H
0,
0C
07
08
0:
0>
0!
0;
0?
19
1=
10
0.
02
03
14
1)
b1 1
b1 6
0#
0'
0$
0(
0%
0*
b101 &
b101 +
#81
1"
1H
1,
1C
17
18
0)
1!
1<
1@
00
1.
13
04
15
1#
1'
#82
0!
0.
0-
0#
0'
1$
1(
#83
08
1)
0@
10
12
05
1#
1'
#84
0"
0H
0,
0C
07
0<
1!
1-
02
03
14
0)
1/
0#
0'
0$
0(
1%
1*
#85
1"
1H
1,
1C
17
18
1)
0/
1<
1@
00
1.
13
04
15
1#
1'
#86
0!
0.
0-
0#
0'
1$
1(
#87
1!
08
0)
1/
0@
10
12
05
1#
1'
#88
0"
0H
0,
0C
07
0<
0!
1-
02
03
14
1)
0/
0#
0'
0$
0(
0%
0*
#89
1"
1H
1,
1C
17
18
0)
1!
1<
1@
00
1.
13
04
15
1#
1'
#90
0!
0.
0-
0#
0'
1$
1(
#91
08
1)
0@
10
12
05
1#
1'
#92
0"
0H
0,
0C
07
0<
1!
1-
02
03
14
0)
1/
0#
0'
0$
0(
1%
1*
#93
1"
1H
1,
1C
17
18
1)
0/
1<
1@
00
1.
13
04
15
1#
1'
#94
0!
0.
0-
0#
0'
1$
1(
#95
1!
08
0)
1/
0@
10
12
05
1#
1'
#96
1"
1D
1H
18
1,
1?
0C
07
1:
1>
0B
0<
0!
09
0=
1A
00
02
03
14
0)
0/
b10 1
b10 6
0#
0'
0$
0(
0%
0*
b110 &
b110 +
#97
0"
0H
0,
0D
08
1)
0?
10
13
04
15
1#
1'
#98
1-
0#
0'
1$
1(
#99
17
0)
1!
1;
00
1.
12
05
1#
1'
#100
1"
1H
1,
1D
07
18
0!
0;
1?
0.
0-
02
03
14
1)
0#
0'
0$
0(
1%
1*
#101
0"
0H
0,
0D
1!
08
0)
1/
0?
10
13
04
15
1#
1'
#102
1-
0#
0'
1$
1(
#103
17
1)
0/
1;
00
1.
12
05
1#
1'
#104
1"
1H
1,
1D
07
18
0!
0;
1?
0.
0-
02
03
14
0)
0#
0'
0$
0(
0%
0*
#105
0"
0H
0,
0D
08
1)
0?
10
13
04
15
1#
1'
#106
1-
0#
0'
1$
1(
#107
17
0)
1!
1;
00
1.
12
05
1#
1'
#108
1"
1H
1,
1D
07
18
0!
0;
1?
0.
0-
02
03
14
1)
0#
0'
0$
0(
1%
1*
#109
0"
0H
0,
0D
1!
08
0)
1/
0?
10
13
04
15
1#
1'
#110
1-
0#
0'
1$
1(
#111
17
1)
0/
1;
00
1.
12
05
1#
1'
#112
0"
0H
0,
0D
07
08
0:
0>
0!
0;
0?
19
1=
10
0.
02
03
14
1)
b11 1
b11 6
0#
0'
0$
0(
0%
0*
b111 &
b111 +
#113
1"
1H
1,
1D
17
18
0)
1!
1<
1@
00
1.
13
04
15
1#
1'
#114
0!
0.
0-
0#
0'
1$
1(
#115
0"
0H
0,
0D
08
1)
0@
10
12
05
1#
1'
#116
07
0<
1!
1-
02
03
14
0)
1/
0#
0'
0$
0(
1%
1*
#117
1"
1H
1,
1D
17
18
1)
0/
1<
1@
00
1.
13
04
15
1#
1'
#118
0!
0.
0-
0#
0'
1$
1(
#119
0"
0H
0,
0D
1!
08
0)
1/
0@
10
12
05
1#
1'
#120
07
0<
0!
1-
02
03
14
1)
0/
0#
0'
0$
0(
0%
0*
#121
1"
1H
1,
1D
17
18
0)
1!
1<
1@
00
1.
13
04
15
1#
1'
#122
0!
0.
0-
0#
0'
1$
1(
#123
0"
0H
0,
0D
08
1)
0@
10
12
05
1#
1'
#124
07
0<
1!
1-
02
03
14
0)
1/
0#
0'
0$
0(
1%
1*
#125
1"
1H
1,
1D
17
18
1)
0/
1<
1@
00
1.
13
04
15
1#
1'
#126
0!
0.
0-
0#
0'
1$
1(
#127
0"
0H
0,
0D
1!
08
0)
1/
0@
10
12
05
1#
1'
#128
07
0<
0!
1-
02
03
14
1)
0/
0#
0'
0$
0(
0%
0*
